{
  "scrapeInfo": {
    "timestamp": "2025-11-07T15:19:04.198Z",
    "version": "1.0.0",
    "url": "https://www.callawaygolf.jp/mens/tops/outer/C25215107_.html?pid=C25215107_1030_L",
    "productId": "C25215107",
    "totalVariants": 4,
    "totalColors": 1,
    "totalSizes": 4,
    "totalImages": 30,
    "processingTimeMs": 2,
    "dataSources": [
      "dom_enhanced"
    ]
  },
  "product": {
    "productId": "C25215107",
    "title": "スターストレッチ2WAY中綿ブルゾン (MENS)",
    "productUrl": "https://www.callawaygolf.jp/mens/tops/outer/C25215107_.html?pid=C25215107_1030_L",
    "description": "",
    "brand": "Callaway Golf",
    "category": "",
    "tags": [],
    "mainImage": "https://www.callawaygolf.jp/_next/image?url=https%3A%2F%2Fcdn2.webdamdb.com%2F1280_Mhknyh47yUN01XV7.jpg%3F1758202534&w=3000&q=90&dpl=dpl_5benJj4UTbfCa9QfUUFQwAkyHADW",
    "detailUrl": "https://www.callawaygolf.jp/mens/tops/outer/C25215107_.html?pid=C25215107_1030_L",
    "sizeChart": {
      "headers": [],
      "rows": []
    }
  },
  "variants": [
    {
      "variantId": "C25215107_1030_S",
      "colorName": "ブルー",
      "colorCode": "1030",
      "sizeName": "S",
      "sizeCode": "S",
      "availability": "unknown",
      "sku": "C25215107_1030_S",
      "priceJPY": null
    },
    {
      "variantId": "C25215107_1030_M",
      "colorName": "ブルー",
      "colorCode": "1030",
      "sizeName": "M",
      "sizeCode": "M",
      "availability": "unknown",
      "sku": "C25215107_1030_M",
      "priceJPY": null
    },
    {
      "variantId": "C25215107_1030_L",
      "colorName": "ブルー",
      "colorCode": "1030",
      "sizeName": "L",
      "sizeCode": "L",
      "availability": "unknown",
      "sku": "C25215107_1030_L",
      "priceJPY": null
    },
    {
      "variantId": "C25215107_1030_LL",
      "colorName": "ブルー",
      "colorCode": "1030",
      "sizeName": "LL",
      "sizeCode": "LL",
      "availability": "unknown",
      "sku": "C25215107_1030_LL",
      "priceJPY": null
    }
  ],
  "colors": [
    {
      "code": "1030",
      "name": "ブルー"
    }
  ],
  "sizes": [
    "S",
    "M",
    "L",
    "LL"
  ],
  "sizeChart": {
    "headers": [],
    "rows": []
  },
  "images": {
    "product": [
      "https://www.callawaygolf.jp/_next/image?url=https%3A%2F%2Fcdn2.webdamdb.com%2F1280_Mhknyh47yUN01XV7.jpg%3F1758202534&w=3000&q=90&dpl=dpl_5benJj4UTbfCa9QfUUFQwAkyHADW",
      "https://www.callawaygolf.jp/_next/image?url=https%3A%2F%2Fcdn2.webdamdb.com%2F1280_IhAxlNpDJs81o32T.jpg%3F1760525520&w=3000&q=90&dpl=dpl_5benJj4UTbfCa9QfUUFQwAkyHADW",
      "https://www.callawaygolf.jp/_next/image?url=https%3A%2F%2Fcdn2.webdamdb.com%2F1280_kpDvdfreSkc15AFM.jpg%3F1758202489&w=3000&q=90&dpl=dpl_5benJj4UTbfCa9QfUUFQwAkyHADW",
      "https://www.callawaygolf.jp/_next/image?url=https%3A%2F%2Fcdn2.webdamdb.com%2F1280_gOpS31Gf21zi9cSm.jpg%3F1760525563&w=3000&q=90&dpl=dpl_5benJj4UTbfCa9QfUUFQwAkyHADW",
      "https://www.callawaygolf.jp/_next/image?url=https%3A%2F%2Fcdn2.webdamdb.com%2F1280_snmFniE5jpF73kAi.jpg%3F1760525580&w=3000&q=90&dpl=dpl_5benJj4UTbfCa9QfUUFQwAkyHADW",
      "https://www.callawaygolf.jp/_next/image?url=https%3A%2F%2Fcdn2.webdamdb.com%2F1280_MUKHdHwTAk01M62F.jpg%3F1760525600&w=3000&q=90&dpl=dpl_5benJj4UTbfCa9QfUUFQwAkyHADW",
      "https://www.callawaygolf.jp/_next/image?url=https%3A%2F%2Fcdn2.webdamdb.com%2F1280_gkY6W68eztD36Izp.jpg%3F1760525614&w=3000&q=90&dpl=dpl_5benJj4UTbfCa9QfUUFQwAkyHADW",
      "https://www.callawaygolf.jp/_next/image?url=https%3A%2F%2Fcdn2.webdamdb.com%2F1280_2vHTIaq0CQK216eG.jpg%3F1760525670&w=3000&q=90&dpl=dpl_5benJj4UTbfCa9QfUUFQwAkyHADW",
      "https://www.callawaygolf.jp/_next/image?url=https%3A%2F%2Fcdn2.webdamdb.com%2F1280_M9Hd9d57kg02EZRs.jpg%3F1760525725&w=3000&q=90&dpl=dpl_5benJj4UTbfCa9QfUUFQwAkyHADW",
      "https://www.callawaygolf.jp/_next/image?url=https%3A%2F%2Fcdn2.webdamdb.com%2F1280_0uQ5BizdWC55cr3n.jpg%3F1760525742&w=3000&q=90&dpl=dpl_5benJj4UTbfCa9QfUUFQwAkyHADW",
      "https://www.callawaygolf.jp/_next/image?url=https%3A%2F%2Fcdn2.webdamdb.com%2F1280_oBFaSfq7i1s01A2w.jpg%3F1760525776&w=3000&q=90&dpl=dpl_5benJj4UTbfCa9QfUUFQwAkyHADW",
      "https://www.callawaygolf.jp/_next/image?url=https%3A%2F%2Fcdn2.webdamdb.com%2F1280_6ihVV1W2VDL21IqF.jpg%3F1760525821&w=3000&q=90&dpl=dpl_5benJj4UTbfCa9QfUUFQwAkyHADW",
      "https://www.callawaygolf.jp/_next/image?url=https%3A%2F%2Fcdn2.webdamdb.com%2F1280_QemYrGfJPNr81ohS.jpg%3F1760525915&w=3000&q=90&dpl=dpl_5benJj4UTbfCa9QfUUFQwAkyHADW",
      "https://www.callawaygolf.jp/_next/image?url=https%3A%2F%2Fcdn2.webdamdb.com%2F1280_gihtKRNhaqK76XHf.jpg%3F1760525962&w=3000&q=90&dpl=dpl_5benJj4UTbfCa9QfUUFQwAkyHADW",
      "https://www.callawaygolf.jp/_next/image?url=https%3A%2F%2Fcdn2.webdamdb.com%2F1280_QbgRAwYH6i432AYh.jpg%3F1760525977&w=3000&q=90&dpl=dpl_5benJj4UTbfCa9QfUUFQwAkyHADW",
      "https://www.callawaygolf.jp/_next/image?url=https%3A%2F%2Fcdn2.webdamdb.com%2F1280_Mhknyh47yUN01XV7.jpg%3F1758202534&w=3000&q=90&dpl=dpl_5benJj4UTbfCa9QfUUFQwAkyHADW",
      "https://www.callawaygolf.jp/_next/image?url=https%3A%2F%2Fcdn2.webdamdb.com%2F1280_IhAxlNpDJs81o32T.jpg%3F1760525520&w=3000&q=90&dpl=dpl_5benJj4UTbfCa9QfUUFQwAkyHADW",
      "https://www.callawaygolf.jp/_next/image?url=https%3A%2F%2Fcdn2.webdamdb.com%2F1280_kpDvdfreSkc15AFM.jpg%3F1758202489&w=3000&q=90&dpl=dpl_5benJj4UTbfCa9QfUUFQwAkyHADW",
      "https://www.callawaygolf.jp/_next/image?url=https%3A%2F%2Fcdn2.webdamdb.com%2F1280_gOpS31Gf21zi9cSm.jpg%3F1760525563&w=3000&q=90&dpl=dpl_5benJj4UTbfCa9QfUUFQwAkyHADW",
      "https://www.callawaygolf.jp/_next/image?url=https%3A%2F%2Fcdn2.webdamdb.com%2F1280_snmFniE5jpF73kAi.jpg%3F1760525580&w=3000&q=90&dpl=dpl_5benJj4UTbfCa9QfUUFQwAkyHADW",
      "https://www.callawaygolf.jp/_next/image?url=https%3A%2F%2Fcdn2.webdamdb.com%2F1280_MUKHdHwTAk01M62F.jpg%3F1760525600&w=3000&q=90&dpl=dpl_5benJj4UTbfCa9QfUUFQwAkyHADW",
      "https://www.callawaygolf.jp/_next/image?url=https%3A%2F%2Fcdn2.webdamdb.com%2F1280_gkY6W68eztD36Izp.jpg%3F1760525614&w=3000&q=90&dpl=dpl_5benJj4UTbfCa9QfUUFQwAkyHADW",
      "https://www.callawaygolf.jp/_next/image?url=https%3A%2F%2Fcdn2.webdamdb.com%2F1280_2vHTIaq0CQK216eG.jpg%3F1760525670&w=3000&q=90&dpl=dpl_5benJj4UTbfCa9QfUUFQwAkyHADW",
      "https://www.callawaygolf.jp/_next/image?url=https%3A%2F%2Fcdn2.webdamdb.com%2F1280_M9Hd9d57kg02EZRs.jpg%3F1760525725&w=3000&q=90&dpl=dpl_5benJj4UTbfCa9QfUUFQwAkyHADW",
      "https://www.callawaygolf.jp/_next/image?url=https%3A%2F%2Fcdn2.webdamdb.com%2F1280_0uQ5BizdWC55cr3n.jpg%3F1760525742&w=3000&q=90&dpl=dpl_5benJj4UTbfCa9QfUUFQwAkyHADW",
      "https://www.callawaygolf.jp/_next/image?url=https%3A%2F%2Fcdn2.webdamdb.com%2F1280_oBFaSfq7i1s01A2w.jpg%3F1760525776&w=3000&q=90&dpl=dpl_5benJj4UTbfCa9QfUUFQwAkyHADW",
      "https://www.callawaygolf.jp/_next/image?url=https%3A%2F%2Fcdn2.webdamdb.com%2F1280_6ihVV1W2VDL21IqF.jpg%3F1760525821&w=3000&q=90&dpl=dpl_5benJj4UTbfCa9QfUUFQwAkyHADW",
      "https://www.callawaygolf.jp/_next/image?url=https%3A%2F%2Fcdn2.webdamdb.com%2F1280_QemYrGfJPNr81ohS.jpg%3F1760525915&w=3000&q=90&dpl=dpl_5benJj4UTbfCa9QfUUFQwAkyHADW",
      "https://www.callawaygolf.jp/_next/image?url=https%3A%2F%2Fcdn2.webdamdb.com%2F1280_gihtKRNhaqK76XHf.jpg%3F1760525962&w=3000&q=90&dpl=dpl_5benJj4UTbfCa9QfUUFQwAkyHADW",
      "https://www.callawaygolf.jp/_next/image?url=https%3A%2F%2Fcdn2.webdamdb.com%2F1280_QbgRAwYH6i432AYh.jpg%3F1760525977&w=3000&q=90&dpl=dpl_5benJj4UTbfCa9QfUUFQwAkyHADW"
    ],
    "variants": {
      "1030": [
        "https://www.callawaygolf.jp/_next/image?url=https%3A%2F%2Fcdn2.webdamdb.com%2F1280_Mhknyh47yUN01XV7.jpg%3F1758202534&w=3000&q=90&dpl=dpl_5benJj4UTbfCa9QfUUFQwAkyHADW",
        "https://www.callawaygolf.jp/_next/image?url=https%3A%2F%2Fcdn2.webdamdb.com%2F1280_IhAxlNpDJs81o32T.jpg%3F1760525520&w=3000&q=90&dpl=dpl_5benJj4UTbfCa9QfUUFQwAkyHADW",
        "https://www.callawaygolf.jp/_next/image?url=https%3A%2F%2Fcdn2.webdamdb.com%2F1280_kpDvdfreSkc15AFM.jpg%3F1758202489&w=3000&q=90&dpl=dpl_5benJj4UTbfCa9QfUUFQwAkyHADW",
        "https://www.callawaygolf.jp/_next/image?url=https%3A%2F%2Fcdn2.webdamdb.com%2F1280_gOpS31Gf21zi9cSm.jpg%3F1760525563&w=3000&q=90&dpl=dpl_5benJj4UTbfCa9QfUUFQwAkyHADW",
        "https://www.callawaygolf.jp/_next/image?url=https%3A%2F%2Fcdn2.webdamdb.com%2F1280_snmFniE5jpF73kAi.jpg%3F1760525580&w=3000&q=90&dpl=dpl_5benJj4UTbfCa9QfUUFQwAkyHADW",
        "https://www.callawaygolf.jp/_next/image?url=https%3A%2F%2Fcdn2.webdamdb.com%2F1280_MUKHdHwTAk01M62F.jpg%3F1760525600&w=3000&q=90&dpl=dpl_5benJj4UTbfCa9QfUUFQwAkyHADW",
        "https://www.callawaygolf.jp/_next/image?url=https%3A%2F%2Fcdn2.webdamdb.com%2F1280_gkY6W68eztD36Izp.jpg%3F1760525614&w=3000&q=90&dpl=dpl_5benJj4UTbfCa9QfUUFQwAkyHADW",
        "https://www.callawaygolf.jp/_next/image?url=https%3A%2F%2Fcdn2.webdamdb.com%2F1280_2vHTIaq0CQK216eG.jpg%3F1760525670&w=3000&q=90&dpl=dpl_5benJj4UTbfCa9QfUUFQwAkyHADW",
        "https://www.callawaygolf.jp/_next/image?url=https%3A%2F%2Fcdn2.webdamdb.com%2F1280_M9Hd9d57kg02EZRs.jpg%3F1760525725&w=3000&q=90&dpl=dpl_5benJj4UTbfCa9QfUUFQwAkyHADW",
        "https://www.callawaygolf.jp/_next/image?url=https%3A%2F%2Fcdn2.webdamdb.com%2F1280_0uQ5BizdWC55cr3n.jpg%3F1760525742&w=3000&q=90&dpl=dpl_5benJj4UTbfCa9QfUUFQwAkyHADW",
        "https://www.callawaygolf.jp/_next/image?url=https%3A%2F%2Fcdn2.webdamdb.com%2F1280_oBFaSfq7i1s01A2w.jpg%3F1760525776&w=3000&q=90&dpl=dpl_5benJj4UTbfCa9QfUUFQwAkyHADW",
        "https://www.callawaygolf.jp/_next/image?url=https%3A%2F%2Fcdn2.webdamdb.com%2F1280_6ihVV1W2VDL21IqF.jpg%3F1760525821&w=3000&q=90&dpl=dpl_5benJj4UTbfCa9QfUUFQwAkyHADW",
        "https://www.callawaygolf.jp/_next/image?url=https%3A%2F%2Fcdn2.webdamdb.com%2F1280_QemYrGfJPNr81ohS.jpg%3F1760525915&w=3000&q=90&dpl=dpl_5benJj4UTbfCa9QfUUFQwAkyHADW",
        "https://www.callawaygolf.jp/_next/image?url=https%3A%2F%2Fcdn2.webdamdb.com%2F1280_gihtKRNhaqK76XHf.jpg%3F1760525962&w=3000&q=90&dpl=dpl_5benJj4UTbfCa9QfUUFQwAkyHADW",
        "https://www.callawaygolf.jp/_next/image?url=https%3A%2F%2Fcdn2.webdamdb.com%2F1280_QbgRAwYH6i432AYh.jpg%3F1760525977&w=3000&q=90&dpl=dpl_5benJj4UTbfCa9QfUUFQwAkyHADW",
        "https://www.callawaygolf.jp/_next/image?url=https%3A%2F%2Fcdn2.webdamdb.com%2F1280_Mhknyh47yUN01XV7.jpg%3F1758202534&w=3000&q=90&dpl=dpl_5benJj4UTbfCa9QfUUFQwAkyHADW",
        "https://www.callawaygolf.jp/_next/image?url=https%3A%2F%2Fcdn2.webdamdb.com%2F1280_IhAxlNpDJs81o32T.jpg%3F1760525520&w=3000&q=90&dpl=dpl_5benJj4UTbfCa9QfUUFQwAkyHADW",
        "https://www.callawaygolf.jp/_next/image?url=https%3A%2F%2Fcdn2.webdamdb.com%2F1280_kpDvdfreSkc15AFM.jpg%3F1758202489&w=3000&q=90&dpl=dpl_5benJj4UTbfCa9QfUUFQwAkyHADW",
        "https://www.callawaygolf.jp/_next/image?url=https%3A%2F%2Fcdn2.webdamdb.com%2F1280_gOpS31Gf21zi9cSm.jpg%3F1760525563&w=3000&q=90&dpl=dpl_5benJj4UTbfCa9QfUUFQwAkyHADW",
        "https://www.callawaygolf.jp/_next/image?url=https%3A%2F%2Fcdn2.webdamdb.com%2F1280_snmFniE5jpF73kAi.jpg%3F1760525580&w=3000&q=90&dpl=dpl_5benJj4UTbfCa9QfUUFQwAkyHADW",
        "https://www.callawaygolf.jp/_next/image?url=https%3A%2F%2Fcdn2.webdamdb.com%2F1280_MUKHdHwTAk01M62F.jpg%3F1760525600&w=3000&q=90&dpl=dpl_5benJj4UTbfCa9QfUUFQwAkyHADW",
        "https://www.callawaygolf.jp/_next/image?url=https%3A%2F%2Fcdn2.webdamdb.com%2F1280_gkY6W68eztD36Izp.jpg%3F1760525614&w=3000&q=90&dpl=dpl_5benJj4UTbfCa9QfUUFQwAkyHADW",
        "https://www.callawaygolf.jp/_next/image?url=https%3A%2F%2Fcdn2.webdamdb.com%2F1280_2vHTIaq0CQK216eG.jpg%3F1760525670&w=3000&q=90&dpl=dpl_5benJj4UTbfCa9QfUUFQwAkyHADW",
        "https://www.callawaygolf.jp/_next/image?url=https%3A%2F%2Fcdn2.webdamdb.com%2F1280_M9Hd9d57kg02EZRs.jpg%3F1760525725&w=3000&q=90&dpl=dpl_5benJj4UTbfCa9QfUUFQwAkyHADW",
        "https://www.callawaygolf.jp/_next/image?url=https%3A%2F%2Fcdn2.webdamdb.com%2F1280_0uQ5BizdWC55cr3n.jpg%3F1760525742&w=3000&q=90&dpl=dpl_5benJj4UTbfCa9QfUUFQwAkyHADW",
        "https://www.callawaygolf.jp/_next/image?url=https%3A%2F%2Fcdn2.webdamdb.com%2F1280_oBFaSfq7i1s01A2w.jpg%3F1760525776&w=3000&q=90&dpl=dpl_5benJj4UTbfCa9QfUUFQwAkyHADW",
        "https://www.callawaygolf.jp/_next/image?url=https%3A%2F%2Fcdn2.webdamdb.com%2F1280_6ihVV1W2VDL21IqF.jpg%3F1760525821&w=3000&q=90&dpl=dpl_5benJj4UTbfCa9QfUUFQwAkyHADW",
        "https://www.callawaygolf.jp/_next/image?url=https%3A%2F%2Fcdn2.webdamdb.com%2F1280_QemYrGfJPNr81ohS.jpg%3F1760525915&w=3000&q=90&dpl=dpl_5benJj4UTbfCa9QfUUFQwAkyHADW",
        "https://www.callawaygolf.jp/_next/image?url=https%3A%2F%2Fcdn2.webdamdb.com%2F1280_gihtKRNhaqK76XHf.jpg%3F1760525962&w=3000&q=90&dpl=dpl_5benJj4UTbfCa9QfUUFQwAkyHADW",
        "https://www.callawaygolf.jp/_next/image?url=https%3A%2F%2Fcdn2.webdamdb.com%2F1280_QbgRAwYH6i432AYh.jpg%3F1760525977&w=3000&q=90&dpl=dpl_5benJj4UTbfCa9QfUUFQwAkyHADW"
      ]
    }
  },
  "ossLinks": {
    "productImages": [],
    "variantImages": {}
  }
}