{
  "products": {
    "product_i7z0mtq5k": {
      "productName": "ルコックゴルフ メンズ ポロシャツ 25SS",
      "price": "￥8,800",
      "gender": "男士",
      "description": "",
      "colors": [],
      "sizes": [],
      "imageUrls": [],
      "sizeChart": {},
      "scrapeInfo": {
        "totalColors": 0,
        "totalSizes": 0,
        "totalImages": 0
      }
    },
    "product_mahn0zbtw": {
      "productName": "ルコックゴルフ レディース ジャケット 25FW",
      "price": "￥12,000",
      "gender": "女士",
      "description": "",
      "colors": [],
      "sizes": [],
      "imageUrls": [],
      "sizeChart": {},
      "scrapeInfo": {
        "totalColors": 0,
        "totalSizes": 0,
        "totalImages": 0
      }
    }
  },
  "total": 2,
  "processed": 2,
  "failed": 0,
  "errors": [],
  "timestamp": "2025-11-15T09:51:00.316Z",
  "brand": "lecoqgolf",
  "batchMode": true
}