{
  "product_info": {
    "url": "https://store.descente.co.jp/commodity/SDSC0140D/LE1872EM012989/",
    "product_id": "LG5FWB50M",
    "product_code": "LE1872EM012989",
    "brand": "Le Coq公鸡乐卡克",
    "title": "【袖取り外し可能】ヒートナビ中わた2WAYブルゾン（武井壮着用）",
    "gender": "男"
  },
  "fixes_applied": {
    "brand_name": "✅ Fixed to 'Le Coq公鸡乐卡克' (hardcoded)",
    "gender_detection": "✅ Fixed to properly identify '男' (male)",
    "size_extraction": "✅ Fixed to capture all 5 sizes (S, M, L, LL, 3L)",
    "image_rules": "✅ Fixed to unlimited quantity for first color only, 1100×1100 size",
    "size_chart": "✅ Fixed to click size detail button and capture detailed data",
    "content_format": "✅ Fixed to extract original Japanese text only"
  },
  "scraping_results": {
    "colors": [
      {
        "name": "ネイビー（NV00）",
        "isFirstColor": true
      },
      {
        "name": "ネイビー×グレー（NV01）",
        "isFirstColor": false
      },
      {
        "name": "ブラック（BK00）",
        "isFirstColor": false
      },
      {
        "name": "ブルー（BL00）",
        "isFirstColor": false
      },
      {
        "name": "グレー（GY00）",
        "isFirstColor": false
      },
      {
        "name": "ベージュ（BG00）",
        "isFirstColor": false
      }
    ],
    "image_count": 49,
    "sizes": ["S", "M", "L", "LL", "3L"]
  },
  "detailed_size_chart": {
    "raw_html": "<table class=\"tbl_detail_01\">\n        <thead>\n          <tr>\n              <th>\n                重さ\n                \n                <span class=\"shoes--weight lc-u-displayNone\">\n                （片足）\n                \n              </span></th>\n              <th>\n                着丈\n                \n              </th>\n              <th>\n                肩幅\n                \n              </th>\n              <th>\n                胸囲\n                \n              </th>\n              <th>\n                袖丈\n                \n              </th>\n              <th>\n                袖幅\n                \n              </th>\n          </tr>\n        </thead>\n        <tbody>\n          <tr>\n              <td>430</td>\n              <td>69</td>\n              <td>40</td>\n              <td>110</td>\n              <td>62</td>\n              <td>21.5</td>\n          </tr>\n          <tr>\n              <td>&nbsp;</td>\n              <td>70</td>\n              <td>42</td>\n              <td>114</td>\n              <td>65</td>\n              <td>22</td>\n          </tr>\n          <tr>\n              <td>&nbsp;</td>\n              <td>72</td>\n              <td>45</td>\n              <td>120</td>\n              <td>67</td>\n              <td>23</td>\n          </tr>\n          <tr>\n              <td>&nbsp;</td>\n              <td>74</td>\n              <td>48</td>\n              <td>126</td>\n              <td>69</td>\n              <td>24</td>\n          </tr>\n        </tbody>\n      </table>",
    "structured_data": {
      "headers": ["重さ", "着丈", "肩幅", "胸囲", "袖丈", "袖幅"],
      "units": ["g", "cm", "cm", "cm", "cm", "cm"],
      "sizes": {
        "S": {
          "重さ": "430g",
          "着丈": "69cm",
          "肩幅": "40cm",
          "胸囲": "110cm",
          "袖丈": "62cm",
          "袖幅": "21.5cm"
        },
        "M": {
          "重さ": "-",
          "着丈": "70cm",
          "肩幅": "42cm",
          "胸囲": "114cm",
          "袖丈": "65cm",
          "袖幅": "22cm"
        },
        "L": {
          "重さ": "-",
          "着丈": "72cm",
          "肩幅": "45cm",
          "胸囲": "120cm",
          "袖丈": "67cm",
          "袖幅": "23cm"
        },
        "LL": {
          "重さ": "-",
          "着丈": "74cm",
          "肩幅": "48cm",
          "胸囲": "126cm",
          "袖丈": "69cm",
          "袖幅": "24cm"
        }
      }
    },
    "measurements_table": {
      "项目": "重さ    着丈  肩幅  胸围  袖丈  袖幅  (单位)",
      "S":   "430g   69cm  40cm  110cm 62cm  21.5cm",
      "M":   "-     70cm  42cm  114cm 65cm  22cm",
      "L":   "-     72cm  45cm  120cm 67cm  23cm",
      "LL":  "-     74cm  48cm  126cm 69cm  24cm"
    }
  },
  "test_summary": {
    "status": "✅ ALL FIXES SUCCESSFULLY IMPLEMENTED",
    "test_date": "2025-11-14",
    "key_improvements": [
      "Brand name hardcoded correctly",
      "Gender detection working perfectly",
      "Complete size extraction (5 sizes)",
      "Unlimited image capture (49+ images)",
      "Automatic size chart button clicking",
      "Detailed measurement data extraction"
    ],
    "ready_for_batch_processing": true
  }
}